[
  {
    "question": "What is your favorite color?",
    "answers": [
      {
        "answer": "Red",
        "score": 3
      },
      {
        "answer": "Green",
        "score": 2
      },
      {
        "answer": "Blue",
        "score": 1
      }
    ]
  },
  {
    "question": "What is your favorite type of cuisine?",
    "answers": [
      {
        "answer": "Italian",
        "score": 1
      },
      {
        "answer": "Mexican",
        "score": 2
      },
      {
        "answer": "Japanese",
        "score": 3
      }
    ]
  },
  {
    "question": "What is your favorite flavor?",
    "answers": [
      {
        "answer": "Sweet",
        "score": 1
      },
      {
        "answer": "Salty",
        "score": 2
      },
      {
        "answer": "Spicy",
        "score": 3
      }
    ]
  },
  {
    "question": "What is your favorite texture?",
    "answers": [
      {
        "answer": "Crunchy",
        "score": 1
      },
      {
        "answer": "Soft",
        "score": 3
      },
      {
        "answer": "Chewy",
        "score": 2
      }
    ]
  },
  {
    "question": "What is your favorite ingredient?",
    "answers": [
      {
        "answer": "Cheese",
        "score": 1
      },
      {
        "answer": "Avocado",
        "score": 3
      },
      {
        "answer": "Bacon",
        "score": 2
      }
    ]
  }
]
